dpath/__init__.py
dpath/exceptions.py
dpath/options.py
dpath/py.typed
dpath/segments.py
dpath/types.py
dpath/util.py
dpath/version.py
dpath-2.1.5.dist-info/LICENSE.txt
dpath-2.1.5.dist-info/METADATA
dpath-2.1.5.dist-info/WHEEL
dpath-2.1.5.dist-info/top_level.txt
dpath-2.1.5.dist-info/RECORD
