Metadata-Version: 2.1
Name: dpath
Version: 2.1.5
Summary: Filesystem-like pathing and searching for dictionaries
Home-page: https://github.com/dpath-maintainers/dpath-python
Author: Caleb Case, Andrew Kesterson
Author-email: calebcase@gmail.com, andrew@aklabs.net
License: MIT
Platform: UNKNOWN
Classifier: Development Status :: 5 - Production/Stable
Classifier: Environment :: Console
Classifier: Intended Audience :: Developers
Classifier: License :: OSI Approved :: MIT License
Classifier: Natural Language :: English
Classifier: Programming Language :: Python :: 3
Classifier: Programming Language :: Python :: 3.7
Classifier: Programming Language :: Python :: 3.8
Classifier: Programming Language :: Python :: 3.9
Classifier: Programming Language :: Python :: 3.10
Classifier: Topic :: Software Development :: Libraries :: Python Modules
Classifier: Typing :: Typed
Requires-Python: >=3.7
License-File: LICENSE.txt
